README.txt
pyramid_gaq.py
setup.cfg
setup.py
pyramid_gaq.egg-info/PKG-INFO
pyramid_gaq.egg-info/SOURCES.txt
pyramid_gaq.egg-info/dependency_links.txt
pyramid_gaq.egg-info/not-zip-safe
pyramid_gaq.egg-info/requires.txt
pyramid_gaq.egg-info/top_level.txt