Metadata-Version: 1.0
Name: pyramid-gaq
Version: 0.0.4
Summary: Lightweight Google Analytics support for pyramid
Home-page: https://github.com/jvanasco/pyramid_gaq
Author: Jonathan Vanasco
Author-email: jonathan@findmeon.com
License: MIT
Keywords: web pyramid
Platform: UNKNOWN
Classifier: Intended Audience :: Developers
Classifier: Framework :: Pylons
Classifier: Programming Language :: Python
Classifier: License :: OSI Approved :: MIT License
